LICENSE
setup.py
smart7_orm/__init__.py
smart7_orm/core.py
smart7_orm/orm_settings.py
smart7_orm/utils.py
smart7_orm/version.py
smart7_orm.egg-info/PKG-INFO
smart7_orm.egg-info/SOURCES.txt
smart7_orm.egg-info/dependency_links.txt
smart7_orm.egg-info/requires.txt
smart7_orm.egg-info/top_level.txt
smart7_orm/db/SQLite.py
smart7_orm/db/__init__.py
smart7_orm/db/base.py
smart7_orm/db/mysql.py
smart7_orm/db/postgreSQL.py
smart7_orm/logger/__init__.py
smart7_orm/logger/logger.py
smart7_orm/models/__init__.py
smart7_orm/models/fields.py
smart7_orm/models/model.py