Metadata-Version: 2.1
Name: smart7-orm
Version: 1.0.4
Summary: tortoise-orm Tools.
Home-page: https://gitee.com/hubertshelley/smart7-orm
Author: Hubert Shelley
Author-email: hubertshelley@163.com
License: Apache Software License
Platform: UNKNOWN
Classifier: License :: OSI Approved :: Apache Software License
Classifier: Programming Language :: Python
Classifier: Programming Language :: Python :: 3
Classifier: Programming Language :: Python :: 3.7
Classifier: Programming Language :: Python :: Implementation :: CPython
Classifier: Programming Language :: Python :: Implementation :: PyPy
Requires-Python: >=3.7.0
License-File: LICENSE
